http_wrap/__init__.py
http_wrap/async_adapters/__init__.py
http_wrap/async_adapters/aiohttp.py
http_wrap/request.py
http_wrap/response.py
http_wrap/sync_adapters/__init__.py
http_wrap/sync_adapters/requests.py
http_wrap-1.0.1.dist-info/LICENSE
http_wrap-1.0.1.dist-info/METADATA
http_wrap-1.0.1.dist-info/WHEEL
http_wrap-1.0.1.dist-info/RECORD
