Metadata-Version: 2.1
Name: http-wrap
Version: 1.0.1
Summary: 
Home-page: https://github.com/bellirodrigo2/http_wrap
License: MIT
Keywords: http,requests,aiohttp
Author: rodbell
Author-email: bellirodrigo2@gmail.com
Requires-Python: >=3.9,<4.0
Classifier: License :: OSI Approved :: MIT License
Classifier: Programming Language :: Python :: 3
Classifier: Programming Language :: Python :: 3.9
Classifier: Programming Language :: Python :: 3.10
Classifier: Programming Language :: Python :: 3.11
Classifier: Programming Language :: Python :: 3.12
Classifier: Programming Language :: Python :: 3.13
Requires-Dist: aiohttp (>=3.11.16,<4.0.0)
Requires-Dist: requests (>=2.32.3,<3.0.0)
Project-URL: Repository, https://github.com/bellirodrigo2/http_wrap
